fletsb/__init__.py
fletsb/__main__.py
fletsb/edit.py
fletsb/load_storyboard.py
fletsb/engines/__init__.py
fletsb/engines/edit_subwidgets_engine.py
fletsb/engines/edit_widget_engine.py
fletsb/engines/suggesting_engine.py
fletsb/engines/viewer_engine.py
fletsb/pages/__init__.py
fletsb/pages/create_new_file.py
fletsb/pages/main_page.py
fletsb/pages/settings.py
fletsb/pages/Settings/__init__.py
fletsb/pages/Settings/pages.py
fletsb/sections/__init__.py
fletsb/sections/edit_section.py
fletsb/sections/left_section.py
fletsb/sections/preview_section.py
fletsb/tools/__init__.py
fletsb/tools/color_picker.py
fletsb/tools/create_storyboard.py
fletsb/tools/get_url_icon.py
fletsb/tools/list_picker.py
fletsb/tools/page_info.py
fletsb/tools/storyboard_class.py
fletsb/ui_toolkit/__init__.py
fletsb/ui_toolkit/widget_browser_frame.py
fletsb/widgets/All.py
fletsb/widgets/__init__.py
fletsb/widgets/widgets/__init__.py
fletsb/widgets/widgets/button.py
fletsb/widgets/widgets/column.py
fletsb/widgets/widgets/image.py
fletsb/widgets/widgets/label.py
fletsb/widgets/widgets/markdown.py
fletsb/widgets/widgets/navigator.py
fletsb/widgets/widgets/open_url.py
fletsb/widgets/widgets/padding.py
fletsb/widgets/widgets/paragraph.py
fletsb/widgets/widgets/row.py
fletsb/widgets/widgets/textfield.py
fletsb/widgets/widgets/title.py
Flet_StoryBoard-1.4.dist-info/LICENSE
Flet_StoryBoard-1.4.dist-info/METADATA
Flet_StoryBoard-1.4.dist-info/WHEEL
Flet_StoryBoard-1.4.dist-info/top_level.txt
Flet_StoryBoard-1.4.dist-info/RECORD
