Metadata-Version: 2.1
Name: Flet-StoryBoard
Version: 1.4
Summary: A UI-Builder that helps programmers build the front-end without codding it.
Home-page: https://github.com/SKbarbon/Flet-StoryBoard
Author: SKbarbon
Classifier: Programming Language :: Python :: 3
Classifier: Operating System :: MacOS :: MacOS X
Classifier: Operating System :: Microsoft :: Windows
License-File: LICENSE
Requires-Dist: flet (==0.5.2)
Requires-Dist: requests
